{
  "connection_graph": {
    "components": [
      {
        "id": "wire-0",
        "label": "wire",
        "bbox": [
          663.0690307617188,
          299.14581298828125,
          1657.7974853515625,
          1069.936279296875
        ],
        "orientation": 0.0,
        "confidence": 0.9026549458503723,
        "component_type": "wire",
        "switch_state": null,
        "connection_points": [
          [
            1056.0,
            299.0
          ],
          [
            1047.0,
            299.0
          ],
          [
            1058.0,
            299.0
          ],
          [
            1232.0,
            299.0
          ],
          [
            1049.0,
            299.0
          ],
          [
            862.0,
            299.0
          ],
          [
            1234.0,
            299.0
          ],
          [
            1082.0,
            299.0
          ],
          [
            864.0,
            299.0
          ],
          [
            1084.0,
            299.0
          ],
          [
            866.0,
            299.0
          ],
          [
            1086.0,
            299.0
          ],
          [
            1227.0,
            299.0
          ],
          [
            1055.0,
            299.0
          ],
          [
            868.0,
            299.0
          ],
          [
            879.0,
            299.0
          ],
          [
            1229.0,
            299.0
          ],
          [
            1046.0,
            299.0
          ],
          [
            1057.0,
            299.0
          ],
          [
            881.0,
            299.0
          ],
          [
            1231.0,
            299.0
          ],
          [
            1048.0,
            299.0
          ],
          [
            1081.0,
            299.0
          ],
          [
            1233.0,
            299.0
          ],
          [
            1050.0,
            299.0
          ],
          [
            863.0,
            299.0
          ],
          [
            1083.0,
            299.0
          ],
          [
            865.0,
            299.0
          ],
          [
            1085.0,
            299.0
          ],
          [
            1230.0,
            299.0
          ],
          [
            1054.0,
            299.0
          ],
          [
            867.0,
            299.0
          ],
          [
            1087.0,
            299.0
          ],
          [
            1228.0,
            299.0
          ],
          [
            880.0,
            299.0
          ]
        ],
        "metadata": {
          "yolo_class_id": 0,
          "detection_index": 0
        }
      },
      {
        "id": "wire-1",
        "label": "unknown_62",
        "bbox": [
          38.91943359375,
          0.0,
          1914.44970703125,
          1065.1392822265625
        ],
        "orientation": 0.0,
        "confidence": 0.11909202486276627,
        "component_type": "wire",
        "switch_state": null,
        "connection_points": [
          [
            576.0,
            0.0
          ],
          [
            1914.0,
            164.0
          ],
          [
            921.0,
            0.0
          ],
          [
            925.0,
            0.0
          ],
          [
            923.0,
            0.0
          ],
          [
            577.0,
            0.0
          ],
          [
            927.0,
            0.0
          ],
          [
            938.0,
            0.0
          ],
          [
            1914.0,
            166.0
          ],
          [
            940.0,
            0.0
          ],
          [
            1914.0,
            614.0
          ],
          [
            38.0,
            887.0
          ],
          [
            572.0,
            0.0
          ],
          [
            583.0,
            0.0
          ],
          [
            38.0,
            313.0
          ],
          [
            1914.0,
            168.0
          ],
          [
            585.0,
            0.0
          ],
          [
            928.0,
            0.0
          ],
          [
            983.0,
            0.0
          ],
          [
            1914.0,
            616.0
          ],
          [
            38.0,
            889.0
          ],
          [
            932.0,
            0.0
          ],
          [
            38.0,
            306.0
          ],
          [
            1914.0,
            161.0
          ],
          [
            930.0,
            0.0
          ],
          [
            573.0,
            0.0
          ],
          [
            934.0,
            0.0
          ],
          [
            945.0,
            0.0
          ],
          [
            38.0,
            891.0
          ],
          [
            575.0,
            0.0
          ],
          [
            38.0,
            354.0
          ],
          [
            936.0,
            0.0
          ],
          [
            947.0,
            0.0
          ],
          [
            38.0,
            308.0
          ],
          [
            1914.0,
            163.0
          ],
          [
            579.0,
            0.0
          ],
          [
            581.0,
            0.0
          ],
          [
            38.0,
            884.0
          ],
          [
            924.0,
            0.0
          ],
          [
            38.0,
            356.0
          ],
          [
            926.0,
            0.0
          ],
          [
            937.0,
            0.0
          ],
          [
            981.0,
            0.0
          ],
          [
            1914.0,
            613.0
          ],
          [
            941.0,
            0.0
          ],
          [
            38.0,
            886.0
          ],
          [
            38.0,
            312.0
          ],
          [
            571.0,
            0.0
          ],
          [
            582.0,
            0.0
          ],
          [
            943.0,
            0.0
          ],
          [
            1914.0,
            170.0
          ],
          [
            38.0,
            888.0
          ],
          [
            584.0,
            0.0
          ],
          [
            38.0,
            305.0
          ],
          [
            920.0,
            0.0
          ],
          [
            38.0,
            890.0
          ],
          [
            922.0,
            0.0
          ],
          [
            933.0,
            0.0
          ],
          [
            38.0,
            307.0
          ],
          [
            1914.0,
            165.0
          ],
          [
            935.0,
            0.0
          ],
          [
            578.0,
            0.0
          ],
          [
            939.0,
            0.0
          ],
          [
            38.0,
            883.0
          ],
          [
            38.0,
            355.0
          ],
          [
            580.0,
            0.0
          ],
          [
            1914.0,
            167.0
          ],
          [
            38.0,
            885.0
          ],
          [
            1914.0,
            615.0
          ],
          [
            980.0,
            0.0
          ],
          [
            929.0,
            0.0
          ],
          [
            984.0,
            0.0
          ],
          [
            38.0,
            314.0
          ],
          [
            1914.0,
            169.0
          ],
          [
            982.0,
            0.0
          ],
          [
            942.0,
            0.0
          ],
          [
            570.0,
            0.0
          ],
          [
            931.0,
            0.0
          ],
          [
            574.0,
            0.0
          ],
          [
            946.0,
            0.0
          ],
          [
            1914.0,
            162.0
          ],
          [
            944.0,
            0.0
          ]
        ],
        "metadata": {
          "yolo_class_id": 62,
          "detection_index": 1
        }
      }
    ],
    "edges": [],
    "state": {
      "is_circuit_closed": false,
      "power_on": true,
      "active_components": [],
      "power_flow_path": [],
      "estimated_voltage": null,
      "estimated_current": null
    },
    "timestamp": 1749676377.835885,
    "frame_id": 4
  },
  "raw_detections": [
    {
      "id": "wire-0",
      "label": "wire",
      "bbox": [
        663.0690307617188,
        299.14581298828125,
        1657.7974853515625,
        1069.936279296875
      ],
      "orientation": 0.0,
      "confidence": 0.9026549458503723,
      "component_type": "wire",
      "switch_state": null,
      "connection_points": [
        [
          1056.0,
          299.0
        ],
        [
          1047.0,
          299.0
        ],
        [
          1058.0,
          299.0
        ],
        [
          1232.0,
          299.0
        ],
        [
          1049.0,
          299.0
        ],
        [
          862.0,
          299.0
        ],
        [
          1234.0,
          299.0
        ],
        [
          1082.0,
          299.0
        ],
        [
          864.0,
          299.0
        ],
        [
          1084.0,
          299.0
        ],
        [
          866.0,
          299.0
        ],
        [
          1086.0,
          299.0
        ],
        [
          1227.0,
          299.0
        ],
        [
          1055.0,
          299.0
        ],
        [
          868.0,
          299.0
        ],
        [
          879.0,
          299.0
        ],
        [
          1229.0,
          299.0
        ],
        [
          1046.0,
          299.0
        ],
        [
          1057.0,
          299.0
        ],
        [
          881.0,
          299.0
        ],
        [
          1231.0,
          299.0
        ],
        [
          1048.0,
          299.0
        ],
        [
          1081.0,
          299.0
        ],
        [
          1233.0,
          299.0
        ],
        [
          1050.0,
          299.0
        ],
        [
          863.0,
          299.0
        ],
        [
          1083.0,
          299.0
        ],
        [
          865.0,
          299.0
        ],
        [
          1085.0,
          299.0
        ],
        [
          1230.0,
          299.0
        ],
        [
          1054.0,
          299.0
        ],
        [
          867.0,
          299.0
        ],
        [
          1087.0,
          299.0
        ],
        [
          1228.0,
          299.0
        ],
        [
          880.0,
          299.0
        ]
      ],
      "metadata": {
        "yolo_class_id": 0,
        "detection_index": 0
      }
    },
    {
      "id": "wire-1",
      "label": "unknown_62",
      "bbox": [
        38.91943359375,
        0.0,
        1914.44970703125,
        1065.1392822265625
      ],
      "orientation": 0.0,
      "confidence": 0.11909202486276627,
      "component_type": "wire",
      "switch_state": null,
      "connection_points": [
        [
          576.0,
          0.0
        ],
        [
          1914.0,
          164.0
        ],
        [
          921.0,
          0.0
        ],
        [
          925.0,
          0.0
        ],
        [
          923.0,
          0.0
        ],
        [
          577.0,
          0.0
        ],
        [
          927.0,
          0.0
        ],
        [
          938.0,
          0.0
        ],
        [
          1914.0,
          166.0
        ],
        [
          940.0,
          0.0
        ],
        [
          1914.0,
          614.0
        ],
        [
          38.0,
          887.0
        ],
        [
          572.0,
          0.0
        ],
        [
          583.0,
          0.0
        ],
        [
          38.0,
          313.0
        ],
        [
          1914.0,
          168.0
        ],
        [
          585.0,
          0.0
        ],
        [
          928.0,
          0.0
        ],
        [
          983.0,
          0.0
        ],
        [
          1914.0,
          616.0
        ],
        [
          38.0,
          889.0
        ],
        [
          932.0,
          0.0
        ],
        [
          38.0,
          306.0
        ],
        [
          1914.0,
          161.0
        ],
        [
          930.0,
          0.0
        ],
        [
          573.0,
          0.0
        ],
        [
          934.0,
          0.0
        ],
        [
          945.0,
          0.0
        ],
        [
          38.0,
          891.0
        ],
        [
          575.0,
          0.0
        ],
        [
          38.0,
          354.0
        ],
        [
          936.0,
          0.0
        ],
        [
          947.0,
          0.0
        ],
        [
          38.0,
          308.0
        ],
        [
          1914.0,
          163.0
        ],
        [
          579.0,
          0.0
        ],
        [
          581.0,
          0.0
        ],
        [
          38.0,
          884.0
        ],
        [
          924.0,
          0.0
        ],
        [
          38.0,
          356.0
        ],
        [
          926.0,
          0.0
        ],
        [
          937.0,
          0.0
        ],
        [
          981.0,
          0.0
        ],
        [
          1914.0,
          613.0
        ],
        [
          941.0,
          0.0
        ],
        [
          38.0,
          886.0
        ],
        [
          38.0,
          312.0
        ],
        [
          571.0,
          0.0
        ],
        [
          582.0,
          0.0
        ],
        [
          943.0,
          0.0
        ],
        [
          1914.0,
          170.0
        ],
        [
          38.0,
          888.0
        ],
        [
          584.0,
          0.0
        ],
        [
          38.0,
          305.0
        ],
        [
          920.0,
          0.0
        ],
        [
          38.0,
          890.0
        ],
        [
          922.0,
          0.0
        ],
        [
          933.0,
          0.0
        ],
        [
          38.0,
          307.0
        ],
        [
          1914.0,
          165.0
        ],
        [
          935.0,
          0.0
        ],
        [
          578.0,
          0.0
        ],
        [
          939.0,
          0.0
        ],
        [
          38.0,
          883.0
        ],
        [
          38.0,
          355.0
        ],
        [
          580.0,
          0.0
        ],
        [
          1914.0,
          167.0
        ],
        [
          38.0,
          885.0
        ],
        [
          1914.0,
          615.0
        ],
        [
          980.0,
          0.0
        ],
        [
          929.0,
          0.0
        ],
        [
          984.0,
          0.0
        ],
        [
          38.0,
          314.0
        ],
        [
          1914.0,
          169.0
        ],
        [
          982.0,
          0.0
        ],
        [
          942.0,
          0.0
        ],
        [
          570.0,
          0.0
        ],
        [
          931.0,
          0.0
        ],
        [
          574.0,
          0.0
        ],
        [
          946.0,
          0.0
        ],
        [
          1914.0,
          162.0
        ],
        [
          944.0,
          0.0
        ]
      ],
      "metadata": {
        "yolo_class_id": 62,
        "detection_index": 1
      }
    }
  ],
  "processing_time": 0.7349638938903809,
  "error_message": null
}