{
  "connection_graph": {
    "components": [
      {
        "id": "wire-0",
        "label": "wire",
        "bbox": [
          523.6317749023438,
          242.66079711914062,
          1609.4293212890625,
          1071.8419189453125
        ],
        "orientation": 0.0,
        "confidence": 0.9170569777488708,
        "component_type": "wire",
        "switch_state": null,
        "connection_points": [],
        "metadata": {
          "yolo_class_id": 0,
          "detection_index": 0
        }
      }
    ],
    "edges": [],
    "state": {
      "is_circuit_closed": false,
      "power_on": true,
      "active_components": [],
      "power_flow_path": [],
      "estimated_voltage": null,
      "estimated_current": null
    },
    "timestamp": 1749676441.083775,
    "frame_id": 4
  },
  "raw_detections": [
    {
      "id": "wire-0",
      "label": "wire",
      "bbox": [
        523.6317749023438,
        242.66079711914062,
        1609.4293212890625,
        1071.8419189453125
      ],
      "orientation": 0.0,
      "confidence": 0.9170569777488708,
      "component_type": "wire",
      "switch_state": null,
      "connection_points": [],
      "metadata": {
        "yolo_class_id": 0,
        "detection_index": 0
      }
    }
  ],
  "processing_time": 0.026346921920776367,
  "error_message": null
}